cfof/__init__.py
cfof/cfof.py
cfof/cfof_isax.py
cfof/fast_cfof.py
cfof-0.4.0.dist-info/LICENSE
cfof-0.4.0.dist-info/METADATA
cfof-0.4.0.dist-info/WHEEL
cfof-0.4.0.dist-info/top_level.txt
cfof-0.4.0.dist-info/RECORD
