Metadata-Version: 2.1
Name: cfof
Version: 0.4.0
Summary: Concentration Free Outlier Factor
Home-page: https://github.com/ghilesmeddour/cfof
Author: Ghiles Meddour
Author-email: ghiles.meddour@munic.io
License: UNKNOWN
Project-URL: Bug Tracker, https://github.com/ghilesmeddour/cfof/issues
Platform: UNKNOWN
Classifier: Programming Language :: Python :: 3
Classifier: Operating System :: OS Independent
Requires-Python: >=3.8
License-File: LICENSE
Requires-Dist: numpy
Requires-Dist: scipy
Requires-Dist: sklearn
